geo_bound/Area.py
geo_bound/Line.py
geo_bound/Map.py
geo_bound/__init__.py
geo_bound/utils/__init__.py
geo_bound/utils/geometry.py
geo_bound/utils/io.py
geo_bound/utils/treat_data.py
geo_bound-0.1.1.dist-info/COPYING.txt
geo_bound-0.1.1.dist-info/LICENSE.txt
geo_bound-0.1.1.dist-info/METADATA
geo_bound-0.1.1.dist-info/WHEEL
geo_bound-0.1.1.dist-info/top_level.txt
geo_bound-0.1.1.dist-info/RECORD
