Metadata-Version: 2.1
Name: geo_bound
Version: 0.1.1
Summary: Location of coordinates in geospatial maps.
Home-page: https://github.com/TDPessoa/geolocation-with-coordinates
Author: TDPessoa
Author-email: thiago.d.pessoa@gmail.com
License: GPL-3.0 license
Classifier: Development Status :: 2 - Pre-Alpha
Classifier: Intended Audience :: Developers
Classifier: License :: Free To Use But Restricted
Classifier: Programming Language :: Python :: 3.11
Classifier: Programming Language :: Python :: 3.12
Classifier: Programming Language :: Python :: 3.13
Classifier: Topic :: Scientific/Engineering :: GIS
Classifier: Topic :: Scientific/Engineering :: Mathematics
Classifier: Topic :: Software Development :: Localization
Classifier: Topic :: Utilities
Requires-Python: >=3.11,<3.14
License-File: LICENSE.txt
License-File: COPYING.txt
